<?xml version="1.0" encoding="UTF-8"?>
<beans xmlns:xsi="http://www.w3.org/2001/XMLSchema-instance"
       xmlns:context="http://www.springframework.org/schema/context"
       xmlns="http://www.springframework.org/schema/beans"
       xsi:schemaLocation="http://www.springframework.org/schema/beans http://www.springframework.org/schema/beans/spring-beans.xsd
		http://www.springframework.org/schema/batch http://www.springframework.org/schema/batch/spring-batch.xsd
		http://www.springframework.org/schema/context http://www.springframework.org/schema/context/spring-context.xsd">

    <!-- Needed if we use a AutomaticJobRegistrar -->
    <context:annotation-config/>

    <context:property-placeholder location="classpath:application.properties" order="1" ignore-unresolvable="true"/>

    <job id="parentJob" abstract="true" xmlns="http://www.springframework.org/schema/batch">
    </job>

    <step id="parentStep" abstract="true" xmlns="http://www.springframework.org/schema/batch">
    </step>

    <bean id="validatorProcessor"
          class="org.springframework.batch.item.validator.ValidatingItemProcessor">
        <property name="validator">
            <bean class="org.springframework.batch.item.validator.SpringValidator">
                <property name="validator">
                    <bean class="org.springframework.validation.beanvalidation.LocalValidatorFactoryBean"/>
                </property>
            </bean>
        </property>
    </bean>

    <bean id="jobParameterExtractor" class="be.raildelays.batch.job.ExecutionContextJobParametersExtractor"/>

</beans>
